voipms/__init__.py
voipms/baseapi.py
voipms/helpers.py
voipms/voipmsclient.py
voipms/entities/__init__.py
voipms/entities/accounts.py
voipms/entities/accountsadd.py
voipms/entities/accountscreate.py
voipms/entities/accountsdelete.py
voipms/entities/accountsget.py
voipms/entities/accountsset.py
voipms/entities/calls.py
voipms/entities/callsdelete.py
voipms/entities/callsget.py
voipms/entities/callssend.py
voipms/entities/callsset.py
voipms/entities/clients.py
voipms/entities/clientsadd.py
voipms/entities/clientsassign.py
voipms/entities/clientsget.py
voipms/entities/clientsset.py
voipms/entities/dids.py
voipms/entities/didsback_order.py
voipms/entities/didscancel.py
voipms/entities/didsconnect.py
voipms/entities/didsdelete.py
voipms/entities/didsget.py
voipms/entities/didsorder.py
voipms/entities/didsremove.py
voipms/entities/didssearch.py
voipms/entities/didssend.py
voipms/entities/didsset.py
voipms/entities/didsunconnect.py
voipms/entities/e911.py
voipms/entities/fax.py
voipms/entities/faxcancel.py
voipms/entities/faxconnect.py
voipms/entities/faxdelete.py
voipms/entities/faxget.py
voipms/entities/faxmail.py
voipms/entities/faxmove.py
voipms/entities/faxorder.py
voipms/entities/faxsearch.py
voipms/entities/faxsend.py
voipms/entities/faxset.py
voipms/entities/faxunconnect.py
voipms/entities/general.py
voipms/entities/generalget.py
voipms/entities/lnp.py
voipms/entities/lnpadd.py
voipms/entities/lnpget.py
voipms/entities/voicemail.py
voipms/entities/voicemailcreate.py
voipms/entities/voicemaildelete.py
voipms/entities/voicemailget.py
voipms/entities/voicemailmark.py
voipms/entities/voicemailmove.py
voipms/entities/voicemailsend.py
voipms/entities/voicemailset.py
voipms-0.2.6.dist-info/LICENSE
voipms-0.2.6.dist-info/METADATA
voipms-0.2.6.dist-info/WHEEL
voipms-0.2.6.dist-info/top_level.txt
voipms-0.2.6.dist-info/RECORD
