Metadata-Version: 2.1
Name: voipms
Version: 0.2.6
Summary: Complete REST API for the voip.ms service
Home-page: https://github.com/4doom4/python-voipms
Author: Maximilian Ebert and Andrew Langemann
Author-email: max.ebert@me.com
Maintainer: Maximilian Ebert and Andrew Langemann
Maintainer-email: max.ebert@me.com
License: MIT
Keywords: voip.ms,voips,api,client,wrapper
Classifier: Development Status :: 3 - Alpha
Classifier: Intended Audience :: Developers
Classifier: Topic :: Software Development :: Libraries :: Python Modules
Classifier: License :: OSI Approved :: MIT License
Classifier: Programming Language :: Python :: 2.7
Classifier: Programming Language :: Python :: 3.4
Classifier: Programming Language :: Python :: 3.5
Classifier: Programming Language :: Python :: 3.6
Classifier: Programming Language :: Python :: 3.7
License-File: LICENSE
Requires-Dist: requests >=2.7.0
